{
  "humboldt-3-20km_vel_mu_wdg_tune_np12": {
    "Albany cxx compiler": "GNU 7.2.0", 
    "Albany git branch": "master", 
    "Albany git commit id": "4d1cf0f", 
    "Simulation start time": "11:43:28", 
    "Trilinos git commit id": "8e46ee67", 
    "case": "humboldt-3-20km_vel_mu_wdg_tune", 
    "date": 13, 
    "np": 12, 
    "passed": true, 
    "timers": {
      "Albany Fill: Jacobian:": 7.42651, 
      "Albany Fill: Residual:": 1.33163, 
      "Albany Jacobian Fill: Evaluate:": 6.89321, 
      "Albany Jacobian Fill: Export:": 0.371756, 
      "Albany Residual Fill: Evaluate:": 1.21966, 
      "Albany Residual Fill: Export:": 0.028655, 
      "Albany Total Time:": 13.2568, 
      "Albany: Setup Time:": 0.546574, 
      "Albany: Total Fill Time:": 8.75936, 
      "NOX Total Linear Solve:": 3.20275, 
      "NOX Total Preconditioner Construction:": 0.644659
    }
  }
}